editmenu/__init__.py
editmenu/editmenu.py
editmenu/getch.py
editmenu-0.0.3.dist-info/LICENSE
editmenu-0.0.3.dist-info/METADATA
editmenu-0.0.3.dist-info/WHEEL
editmenu-0.0.3.dist-info/top_level.txt
editmenu-0.0.3.dist-info/RECORD
