Metadata-Version: 2.1
Name: editmenu
Version: 0.0.3
Summary: A simple multiline edit menu for CLI
Home-page: https://github.com/aswin4400/editmenu.git
Author: Aswin Rajasekharan
Author-email: aswin4400@gmail.com
License: UNKNOWN
Platform: UNKNOWN
Classifier: Programming Language :: Python :: 3
Classifier: License :: OSI Approved :: MIT License
Classifier: Operating System :: OS Independent
Requires-Python: >=3.6
